Workbook

Sheet CASH BOOK
B2: CASH BOOK
B4: APEX SKYLINE DEVELOPERS PVT. LTD.
B5: General Ledger - HDFC Bank Current Account | Period: 01-AUG-2026 to 31-AUG-2026
B7: Date | C7: Ref / Chq. No. | D7: Particulars | E7: Receipts / Dr (₹) | F7: Payments / Cr (₹) | G7: Recon Key | H7: Match Status
B8: 46235 | C8: OB-001 | D8: Opening Balance b/d | E8: 1500000 | F8: 0 | G8: =C8&"_"&(E8+F8) -> OB-001_1500000 | H8: Opening Balance
B9: 46239 | C9: TXN-CB-102 | D9: Booking Advance - Flat 402 (R. Sharma) | E9: 500000 | F9: 0 | G9: =C9&"_"&(E9+F9) -> TXN-CB-102_500000 | H9: =IF(ISNUMBER(_xlfn.XMATCH(G9,'BANK STATEMENT'!$I$10:$I$17)),"Cleared","Uncleared") -> Cleared
B10: 46243 | C10: CHQ-501 | D10: Ultratech Cement Suppliers | E10: 0 | F10: 320000 | G10: =C10&"_"&(E10+F10) -> CHQ-501_320000 | H10: =IF(ISNUMBER(_xlfn.XMATCH(G10,'BANK STATEMENT'!$I$10:$I$17)),"Cleared","Uncleared") -> Cleared
B11: 46248 | C11: CHQ-502 | D11: JSW Steel Infrastructure | E11: 0 | F11: 450000 | G11: =C11&"_"&(E11+F11) -> CHQ-502_450000 | H11: =IF(ISNUMBER(_xlfn.XMATCH(G11,'BANK STATEMENT'!$I$10:$I$17)),"Cleared","Uncleared") -> Cleared
B12: 46254 | C12: TXN-CB-105 | D12: Booking Advance - Villa 12 (A. Verma) | E12: 750000 | F12: 0 | G12: =C12&"_"&(E12+F12) -> TXN-CB-105_750000 | H12: =IF(ISNUMBER(_xlfn.XMATCH(G12,'BANK STATEMENT'!$I$10:$I$17)),"Cleared","Uncleared") -> Uncleared
B13: 46259 | C13: CHQ-503 | D13: Civil Contractor Interim Bill | E13: 0 | F13: 600000 | G13: =C13&"_"&(E13+F13) -> CHQ-503_600000 | H13: =IF(ISNUMBER(_xlfn.XMATCH(G13,'BANK STATEMENT'!$I$10:$I$17)),"Cleared","Uncleared") -> Uncleared
B14: 46262 | C14: CHQ-504 | D14: MEP Subcontractor Payment | E14: 0 | F14: 280000 | G14: =C14&"_"&(E14+F14) -> CHQ-504_280000 | H14: =IF(ISNUMBER(_xlfn.XMATCH(G14,'BANK STATEMENT'!$I$10:$I$17)),"Cleared","Uncleared") -> Cleared
B15: 46265 | C15: TXN-CB-108 | D15: Booking Advance - Office Space 101 | E15: 400000 | F15: 0 | G15: =C15&"_"&(E15+F15) -> TXN-CB-108_400000 | H15: =IF(ISNUMBER(_xlfn.XMATCH(G15,'BANK STATEMENT'!$I$10:$I$17)),"Cleared","Uncleared") -> Cleared
D16: Total | E16: =SUM(E8:E15) -> 3150000 | F16: =SUM(F8:F15) -> 1650000

Sheet BANK STATEMENT
B2: BANK STATEMENT
B4: HDFC BANK LTD. - CORPORATE BANKING DIVISION
B5: Account Name: Apex Skyline Developers Pvt. Ltd. | Account No: 50200089213451 | IFSC: HDFC0001234
B6: Statement Period: 01-AUG-2026 to 31-AUG-2026 | Currency: INR (₹)
B8: TXN Date | C8: Value Date | D8: Narration / Description | E8: Chq / Ref No. | F8: Withdrawals / Dr (₹) | G8: Deposits / Cr (₹) | H8: Balance (₹) | I8: Recon Key | J8: Match Status
B9: 46235 | C9: 46235 | D9: OPENING BALANCE B/F | F9: 0 | G9: 0 | H9: 1500000 | J9: Opening Balance
B10: 46240 | C10: 46240 | D10: CLG/R SHARMA/ADV FL 402 | E10: TXN-CB-102 | F10: 0 | G10: 500000 | H10: =H9-F10+G10 -> 2000000 | I10: =E10&"_"&(F10+G10) -> TXN-CB-102_500000 | J10: =IF(ISNUMBER(_xlfn.XMATCH(I10,'CASH BOOK'!$G$8:$G$15)),"Matched","Bank-Originated Entry") -> Matched
B11: 46245 | C11: 46245 | D11: CLG/ULTRATECH CEMENT | E11: CHQ-501 | F11: 320000 | G11: 0 | H11: =H10-F11+G11 -> 1680000 | I11: =E11&"_"&(F11+G11) -> CHQ-501_320000 | J11: =IF(ISNUMBER(_xlfn.XMATCH(I11,'CASH BOOK'!$G$8:$G$15)),"Matched","Bank-Originated Entry") -> Matched
B12: 46251 | C12: 46251 | D12: CLG/JSW STEEL INFRA | E12: CHQ-502 | F12: 450000 | G12: 0 | H12: =H11-F12+G12 -> 1230000 | I12: =E12&"_"&(F12+G12) -> CHQ-502_450000 | J12: =IF(ISNUMBER(_xlfn.XMATCH(I12,'CASH BOOK'!$G$8:$G$15)),"Matched","Bank-Originated Entry") -> Matched
B13: 46264 | C13: 46264 | D13: CLG/MEP SUBCONTRACT | E13: CHQ-504 | F13: 280000 | G13: 0 | H13: =H12-F13+G13 -> 950000 | I13: =E13&"_"&(F13+G13) -> CHQ-504_280000 | J13: =IF(ISNUMBER(_xlfn.XMATCH(I13,'CASH BOOK'!$G$8:$G$15)),"Matched","Bank-Originated Entry") -> Matched
B14: 46265 | C14: 46265 | D14: RTGS/INFLOW COLL REC | E14: TXN-CB-108 | F14: 0 | G14: 400000 | H14: =H13-F14+G14 -> 1350000 | I14: =E14&"_"&(F14+G14) -> TXN-CB-108_400000 | J14: =IF(ISNUMBER(_xlfn.XMATCH(I14,'CASH BOOK'!$G$8:$G$15)),"Matched","Bank-Originated Entry") -> Matched
B15: 46265 | C15: 46265 | D15: AUTO CR SWEEP INT/AUG26 | E15: INT-9921 | F15: 0 | G15: 12500 | H15: =H14-F15+G15 -> 1362500 | I15: =E15&"_"&(F15+G15) -> INT-9921_12500 | J15: =IF(ISNUMBER(_xlfn.XMATCH(I15,'CASH BOOK'!$G$8:$G$15)),"Matched","Bank-Originated Entry") -> Bank-Originated Entry
B16: 46265 | C16: 46265 | D16: DR/PROJECT TERM LOAN INT | E16: LOAN-883 | F16: 85000 | G16: 0 | H16: =H15-F16+G16 -> 1277500 | I16: =E16&"_"&(F16+G16) -> LOAN-883_85000 | J16: =IF(ISNUMBER(_xlfn.XMATCH(I16,'CASH BOOK'!$G$8:$G$15)),"Matched","Bank-Originated Entry") -> Bank-Originated Entry
B17: 46265 | C17: 46265 | D17: A/C MAINT & INSP CHG/Q2 | E17: CHG-1102 | F17: 4500 | G17: 0 | H17: =H16-F17+G17 -> 1273000 | I17: =E17&"_"&(F17+G17) -> CHG-1102_4500 | J17: =IF(ISNUMBER(_xlfn.XMATCH(I17,'CASH BOOK'!$G$8:$G$15)),"Matched","Bank-Originated Entry") -> Bank-Originated Entry

Sheet BRS DASHBOARD
B2: BANK RECONCILIATION STATEMENT
B4: APEX SKYLINE DEVELOPERS PVT. LTD.
B5: As of 31-AUG-2026 | Reconciled against HDFC Current A/c No. 50200089213451
B7: Particulars | C7: Ref / Description | D7: Details (₹) | E7: Net Amount (₹)
B8: Balance as per Cash Book (Bank Column) | C8: Closing Ledger Position | E8: ='CASH BOOK'!E16-'CASH BOOK'!F16 -> 1500000
B9: Add:
B10: Cheques issued but not presented for payment | C10: CHQ-503 (Civil Contractor) | D10: ='CASH BOOK'!F13 -> 600000 | E10: 0
B11: Direct Credit by Bank (Auto Sweep Interest) | C11: INT-9921 | D11: ='BANK STATEMENT'!G15 -> 12500 | E11: =SUM(D10:D11) -> 612500
B12: Subtotal | E12: =E8+E11 -> 2112500
B13: Less:
B14: Cheques deposited but not cleared by bank | C14: TXN-CB-105 (Villa 12 Adv) | D14: ='CASH BOOK'!E12 -> 750000 | E14: 0
B15: Bank debit for Project Term Loan Interest | C15: LOAN-883 | D15: ='BANK STATEMENT'!F16 -> 85000 | E15: 0
B16: Bank charges & Inspection fees debited | C16: CHG-1102 | D16: ='BANK STATEMENT'!F17 -> 4500 | E16: =SUM(D14:D16) -> 839500
B17: Balance as per Bank Statement | C17: HDFC Statement Closing | D17: 0 | E17: =E12-E16 -> 1273000
B19: Reconciliation Status | E19: =IF(E17='BANK STATEMENT'!H17, "RECONCILED / ZERO VARIANCE", "VARIANCE DETECTED") -> RECONCILED / ZERO VARIANCE
